update_submodules/__init__.py
update_submodules/git.py
update_submodules/github.py
update_submodules/meta_branch.py
update_submodules-0.0.2.dist-info/METADATA
update_submodules-0.0.2.dist-info/WHEEL
update_submodules-0.0.2.dist-info/entry_points.txt
update_submodules-0.0.2.dist-info/top_level.txt
update_submodules-0.0.2.dist-info/RECORD
